cryogen/__init__.py
cryogen/cli.py
cryogen/consolidate.py
cryogen/constants.py
cryogen/parquet.py
cryogen/utils.py
cryogen-0.2.5.dist-info/METADATA
cryogen-0.2.5.dist-info/WHEEL
cryogen-0.2.5.dist-info/entry_points.txt
cryogen-0.2.5.dist-info/RECORD
