Metadata-Version: 2.1
Name: cryogen
Version: 0.2.5
Summary: helps you preserve an ethereum dataset
Home-page: https://github.com/banteg/cryogen
License: MIT
Author: banteg
Requires-Python: >=3.10
Classifier: License :: OSI Approved :: MIT License
Classifier: Programming Language :: Python :: 3
Classifier: Programming Language :: Python :: 3.10
Classifier: Programming Language :: Python :: 3.11
Requires-Dist: pyarrow (>=13.0.0)
Requires-Dist: rich (>=13.5.2)
Requires-Dist: typer (>=0.9.0)
Project-URL: Repository, https://github.com/banteg/cryogen
